[{
		"artist":	"Ichiko",
		"title":	"Koi no Mahou [Maburaho]",
		"url":	"https://www.youtube.com/watch?v=apU1mro9xUo",
		"status":	"present"
	}, {
		"artist":	"Tsukikage",
		"title":	"Spatto! Spy & Spyce [Release the Spyce]",
		"url":	"https://www.youtube.com/watch?v=8KO-beK-48s",
		"status":	"present"
	}, {
		"artist":	"Nakanoke no Itsuzugo",
		"title":	"Gotoubun no Kimochi [5-toubun no Hanayome]",
		"url":	"https://www.youtube.com/watch?v=tF04aIba5p8",
		"status":	"present"
	}, {
		"artist":	"Shoko Nakagawa",
		"title":	"Sorairo Days [Tengen Toppa Gurren Lagann]",
		"url":	"https://www.youtube.com/watch?v=5EXFilTUiko",
		"status":	"present"
	}, {
		"artist":	"",
		"title":	"Ambiguous [Kill la Kill]",
		"url":	"https://www.youtube.com/watch?v=Z6BF_5p4jMY",
		"status":	"present"
	}, {
		"artist":	"",
		"title":	"Sirius [Kill la Kill]",
		"url":	"https://www.youtube.com/watch?v=k62_N6O2esw",
		"status":	"present"
	}, {
		"artist":	"",
		"title":	"Rightfully [Goblin Slayer]",
		"url":	"https://www.youtube.com/watch?v=7z4WJAEG3u8",
		"status":	"present"
	}, {
		"artist":	"",
		"title":	"A Cruel Angel's Thesis [Neon Genesis Evangelion]",
		"url":	"https://www.youtube.com/watch?v=nU21rCWkuJw",
		"status":	"error"
	}, {
		"artist":	"",
		"title":	"Driver's High [Great Teacher Onizuka]",
		"url":	"https://www.youtube.com/watch?v=phAoChN1nC4",
		"status":	"present"
	}, {
		"artist":	"",
		"title":	"Hitori no Yoru [Great Teacher Onizuka]",
		"url":	"https://www.youtube.com/watch?v=xpAg0spgFJA",
		"status":	"present"
	}, {
		"artist":	"",
		"title":	"Hyadain no Kakakata Kataomoi [Nichijou]",
		"url":	"https://www.youtube.com/watch?v=qUk1ZoCGqsA",
		"status":	"present"
	}, {
		"artist":	"",
		"title":	"Hyadain no Joujou Yuujou [Nichijou]",
		"url":	"https://www.youtube.com/watch?v=LB7kQN6uNok",
		"status":	"present"
	}, {
		"artist":	"",
		"title":	"Gotobun no Katachi [The Quintessential Quintuplets 2]",
		"url":	"https://www.youtube.com/watch?v=2oQSUoGhEBg",
		"status":	"present"
	}, {
		"artist":	"",
		"title":	"Chase the World [Accel World]",
		"url":	"https://www.youtube.com/watch?v=uTErr5pGmZc",
		"status":	"present"
	}, {
		"artist":	"",
		"title":	"Burst the Gravity [Accel World]",
		"url":	"https://www.youtube.com/watch?v=IGRAfhYEYKM",
		"status":	"present"
	}, {
		"artist":	"",
		"title":	"Skyreach [Akame Ga Kill]",
		"url":	"https://www.youtube.com/watch?v=vqshxf8WiHE",
		"status":	"present"
	}, {
		"artist":	"",
		"title":	"Liar Mask [Akame Ga kill]",
		"url":	"https://www.youtube.com/watch?v=PRvv-vL0i50",
		"status":	"present"
	}, {
		"artist":	"",
		"title":	"Angel Beats! [Angel Beats]",
		"url":	"https://www.youtube.com/watch?v=zIFV8UUs1-c",
		"status":	"present"
	}, {
		"artist":	"",
		"title":	"Aoi Shiori [Anohana]",
		"url":	"https://www.youtube.com/watch?v=o1JrFtycErY",
		"status":	"error"
	}, {
		"artist":	"",
		"title":	"Core Pride [Blue Exorcist]",
		"url":	"https://www.youtube.com/watch?v=80-W822k6Vw",
		"status":	"error"
	}, {
		"artist":	"",
		"title":	"In my World [Blue Exorcist]",
		"url":	"https://www.youtube.com/watch?v=IBG6WHUNkj4",
		"status":	"error"
	}, {
		"artist":	"",
		"title":	"Soramimi Cake [Azumanga Daioh]",
		"url":	"https://www.youtube.com/watch?v=bsGAsJBW6zM",
		"status":	"present"
	}, {
		"artist":	"",
		"title":	"Staple Staple [Bakemonogatari]",
		"url":	"https://www.youtube.com/watch?v=BoYIjlZRar0",
		"status":	"present"
	}, {
		"artist":	"",
		"title":	"Kaerimichi [Bakemonogatari]",
		"url":	"https://www.youtube.com/watch?v=Pnua0NO0McM",
		"status":	"present"
	}, {
		"artist":	"",
		"title":	"Ambivalent World [Bakemonogatari]",
		"url":	"https://www.youtube.com/watch?v=JAOWmgeKvxE",
		"status":	"present"
	}, {
		"artist":	"",
		"title":	"Ren'ai Circulation [Bakemonogatari]",
		"url":	"https://www.youtube.com/watch?v=uKxyLmbOc0Q",
		"status":	"present"
	}, {
		"artist":	"",
		"title":	"Sugar Sweet Nightmare [Bakemonogatari]",
		"url":	"https://www.youtube.com/watch?v=DOTi2YB726I",
		"status":	"present"
	}, {
		"artist":	"",
		"title":	"Red Fraction [Black Lagoon]",
		"url":	"https://www.youtube.com/watch?v=i9Mw4NSM0bk",
		"status":	"present"
	}, {
		"artist":	"",
		"title":	"Tank! [Cowboy Bebop]",
		"url":	"https://www.youtube.com/watch?v=EL-D9LrFJd4",
		"status":	"present"
	}, {
		"artist":	"",
		"title":	"Kiss of Death [Darling in the FranXX]",
		"url":	"https://www.youtube.com/watch?v=A4kLcDWBYcQ",
		"status":	"present"
	}, {
		"artist":	"",
		"title":	"Flyers [Death Parade]",
		"url":	"https://www.youtube.com/watch?v=_DwbXmr70C0",
		"status":	"present"
	}, {
		"artist":	"",
		"title":	"Cryi for Rain [Domestic Girlfriend]",
		"url":	"https://www.youtube.com/watch?v=0YF8vecQWYs",
		"status":	"present"
	}, {
		"artist":	"",
		"title":	"Good Morning World! [Dr. Stone]",
		"url":	"https://www.youtube.com/watch?v=tF4faMbs5oQ",
		"status":	"present"
	}, {
		"artist":	"",
		"title":	"Sangenshoku [Dr. Stone]",
		"url":	"https://www.youtube.com/watch?v=SohCAjC-Npk",
		"status":	"present"
	}, {
		"artist":	"",
		"title":	"Rakuen [Dr. Stone: Stone Wars]",
		"url":	"https://www.youtube.com/watch?v=34wlhlQpidc",
		"status":	"present"
	}, {
		"artist":	"",
		"title":	"Onegai Muscle [How Heavy are the Dumbbells you Lift?]",
		"url":	"https://www.youtube.com/watch?v=Ayi2CJU2xmQ",
		"status":	"present"
	}, {
		"artist":	"",
		"title":	"Sunset of Betrayal [Durarara!!]",
		"url":	"https://www.youtube.com/watch?v=sk3ZJslK2ks",
		"status":	"present"
	}, {
		"artist":	"",
		"title":	"Complication [Durarara!!]",
		"url":	"https://www.youtube.com/watch?v=PGoHzoZ2OI0",
		"status":	"error"
	}, {
		"artist":	"",
		"title":	"Headhunt [Durarara!!x2 Shou]",
		"url":	"https://www.youtube.com/watch?v=t7wv4InYAl8",
		"status":	"present"
	}, {
		"artist":	"",
		"title":	"Day you Laugh [Durarara!!x2 Ten]",
		"url":	"https://www.youtube.com/watch?v=S5pi8L81YFI",
		"status":	"present"
	}, {
		"artist":	"",
		"title":	"Steppin' Out [Durarara!!x2 Ketsu]",
		"url":	"https://www.youtube.com/watch?v=DPtFrCODF2I",
		"status":	"present"
	}, {
		"artist":	"",
		"title":	"Inferno [Fire Force]",
		"url":	"https://www.youtube.com/watch?v=JBqxVX_LXvk",
		"status":	"present"
	}, {
		"artist":	"",
		"title":	"Mayday [Fire Force]",
		"url":	"https://www.youtube.com/watch?v=t0WClcc-aVs",
		"status":	"present"
	}, {
		"artist":	"",
		"title":	"Spark Again [Fire Force Season 2]",
		"url":	"https://www.youtube.com/watch?v=xLGtT8WuidM",
		"status":	"present"
	}, {
		"artist":	"",
		"title":	"Torch of Liberty [Fire Force Season 2]",
		"url":	"https://www.youtube.com/watch?v=RWLVwB7I48E",
		"status":	"error"
	}, {
		"artist":	"",
		"title":	"Eiyuu Unmei no Uta [Fate Apocrypha]",
		"url":	"https://www.youtube.com/watch?v=3nLH06ftkL0",
		"status":	"error"
	}, {
		"artist":	"",
		"title":	"Ash [Fate Apocrypha]",
		"url":	"https://www.youtube.com/watch?v=DF38s43Qywc",
		"status":	"error"
	}, {
		"artist":	"",
		"title":	"Disillusion [Fate Stay Night]",
		"url":	"https://www.youtube.com/watch?v=Qy7Q77ZD_ME",
		"status":	"present"
	}, {
		"artist":	"",
		"title":	"Kirameku Namida wa Hoshi ni [Fate Stay Night]",
		"url":	"https://www.youtube.com/watch?v=wYTUYpAlZtw",
		"status":	"present"
	}, {
		"artist":	"",
		"title":	"Oath Sign [Fate Zero]",
		"url":	"https://www.youtube.com/watch?v=aK2-jBqwEWU",
		"status":	"present"
	}, {
		"artist":	"",
		"title":	"Melissa [Fullmetal Alchemist]",
		"url":	"https://www.youtube.com/watch?v=uMsOlhzPEfY&t=4s",
		"status":	"present"
	}, {
		"artist":	"",
		"title":	"Ready Steady Go [Fullmetal Alchemist]",
		"url":	"https://www.youtube.com/watch?v=Z8Su678ZVQs",
		"status":	"present"
	}, {
		"artist":	"",
		"title":	"Undo [Fullmetal Alchemist]",
		"url":	"https://www.youtube.com/watch?v=SBbGJ_8JPhU",
		"status":	"present"
	}, {
		"artist":	"",
		"title":	"Rewrite [Fullmetal Alchemist]",
		"url":	"https://www.youtube.com/watch?v=oPg1J79sgkQ",
		"status":	"present"
	}, {
		"artist":	"",
		"title":	"Gabriel Drop Kick [Gabriel DropOut]",
		"url":	"https://www.youtube.com/watch?v=e0oitN2clAw",
		"status":	"present"
	}, {
		"artist":	"",
		"title":	"Kimi ja Nakya Dame Mitai [Gekkan Shoujo Nozaki kun]",
		"url":	"https://www.youtube.com/watch?v=i1qrQWyuM3U",
		"status":	"present"
	}, {
		"artist":	"",
		"title":	"G P [Great Pretender]",
		"url":	"https://www.youtube.com/watch?v=Yjv_yFgHYc0",
		"status":	"present"
	}, {
		"artist":	"",
		"title":	"My Dearest [Guilty Crown]",
		"url":	"https://www.youtube.com/watch?v=WrcL2TBbI5k",
		"status":	"present"
	}, {
		"artist":	"",
		"title":	"The Everlasting Guilty Crown [Guilty Crown]",
		"url":	"https://www.youtube.com/watch?v=-p0IjnBhG10",
		"status":	"present"
	}, {
		"artist":	"",
		"title":	"Highschool of the Dead [Highschool of the Dead]",
		"url":	"https://www.youtube.com/watch?v=TQwQMeb-44g",
		"status":	"present"
	}, {
		"artist":	"",
		"title":	"Easy Love [Don't Toy with Me, Miss Nagatoro]",
		"url":	"https://www.youtube.com/watch?v=x-AHnwQPf9s",
		"status":	"present"
	}, {
		"artist":	"",
		"title":	"Straight Jet [Infinite Stratos]",
		"url":	"https://www.youtube.com/watch?v=ITHQca2MD5k",
		"status":	"error"
	}, {
		"artist":	"",
		"title":	"DeCIDE [How Not to Summon a Demon Lord]",
		"url":	"https://www.youtube.com/watch?v=aKgpEHl8lNc",
		"status":	"error"
	}, {
		"artist":	"",
		"title":	"Everybodey! Everybodey! [How Not to Summon a Demon Lord 2]",
		"url":	"https://www.youtube.com/watch?v=AU0mHZFX0fA",
		"status":	"present"
	}, {
		"artist":	"",
		"title":	"Isekai Quartet [Isekai Quartet]",
		"url":	"https://www.youtube.com/watch?v=KH6fAUWkg3Q",
		"status":	"present"
	}, {
		"artist":	"",
		"title":	"Isekai Showtime [Isekai Quartet 2]",
		"url":	"https://www.youtube.com/watch?v=unmF1BGdVfY",
		"status":	"present"
	}, {
		"artist":	"",
		"title":	"Ikouze Paradise [Interspecies Reviewers]",
		"url":	"https://www.youtube.com/watch?v=RR6kzUMimSI",
		"status":	"present"
	}, {
		"artist":	"",
		"title":	"Kyuukoku Unbalance [I Don't Want to Get Hurt, so I'll Max Out My Defense]",
		"url":	"https://www.youtube.com/watch?v=vS8YwJ9FIrY",
		"status":	"present"
	}, {
		"artist":	"",
		"title":	"Fightin Pose [The Great Jahy Will Not Be Defeated!]",
		"url":	"https://www.youtube.com/watch?v=3FLnQJKOhRc",
		"status":	"present"
	}, {
		"artist":	"",
		"title":	"Seikatsu Konkyuu Dame Dinero [The Great Jahy Will Not Be Defeated!]",
		"url":	"https://www.youtube.com/watch?v=HIKbRqPK_m4",
		"status":	"present"
	}, {
		"artist":	"",
		"title":	"Sono Chi no Sadame [JoJo's Bizarre Adventure part 1]",
		"url":	"https://www.youtube.com/watch?v=73XLX1Br9po",
		"status":	"present"
	}, {
		"artist":	"",
		"title":	"Bloody Stream [JoJo's Bizarre Adventure part 2]",
		"url":	"https://www.youtube.com/watch?v=hmpJqJLsR48",
		"status":	"present"
	}, {
		"artist":	"",
		"title":	"Cagayake! GIRLS [K-On!]",
		"url":	"https://www.youtube.com/watch?v=bwpK5QJu6K4",
		"status":	"error"
	}, {
		"artist":	"",
		"title":	"Go! Go! Maniac [K-On!!]",
		"url":	"https://www.youtube.com/watch?v=plAY6-JX7hc",
		"status":	"error"
	}, {
		"artist":	"",
		"title":	"Utauyo!! MIRACLE [K-On!!]",
		"url":	"https://www.youtube.com/watch?v=B7A9j2GT_5g",
		"status":	"error"
	}, {
		"artist":	"",
		"title":	"Love Dramatic [Kaguya sama: Love is War]",
		"url":	"https://www.youtube.com/watch?v=NcJvsczntO0",
		"status":	"error"
	}, {
		"artist":	"",
		"title":	"Zankoku na Yume to Nemure [Redo of Healer]",
		"url":	"https://www.youtube.com/watch?v=rbXAjYNr6Ac",
		"status":	"error"
	}, {
		"artist":	"",
		"title":	"Miiro [KanColle: Kantai Collection]",
		"url":	"https://www.youtube.com/watch?v=DmHPtZ0RpPA",
		"status":	"present"
	}, {
		"artist":	"",
		"title":	"Hakushi Kassai Uta Awase [Katanagatari]",
		"url":	"https://www.youtube.com/watch?v=9wNuMDvD6h0",
		"status":	"present"
	}, {
		"artist":	"",
		"title":	"Katana to Saya [Katanagatari]",
		"url":	"https://www.youtube.com/watch?v=tTAto8blwF8",
		"status":	"present"
	}, {
		"artist":	"",
		"title":	"Gurenge [Demon slayer]",
		"url":	"https://www.youtube.com/watch?v=jiJu4K2jems",
		"status":	"error"
	}, {
		"artist":	"",
		"title":	"Akeboshi [Demon Slayer: Mugen Train Arc]",
		"url":	"https://www.youtube.com/watch?v=8-K2Xo1EEkE",
		"status":	"error"
	}, {
		"artist":	"",
		"title":	"Zankyou Zanka [Demon Slayer: Entertainment District Arc]",
		"url":	"https://www.youtube.com/watch?v=9YncCMYoNyc",
		"status":	"error"
	}, {
		"artist":	"",
		"title":	"Let me Hear [Parasyte: The Maxim]",
		"url":	"https://www.youtube.com/watch?v=Rm8UjBAS3cs",
		"status":	"present"
	}, {
		"artist":	"",
		"title":	"Fantastic Dreamer [Konosuba]",
		"url":	"https://www.youtube.com/watch?v=sJZvGUC5a5g",
		"status":	"error"
	}, {
		"artist":	"",
		"title":	"Tomorrow [Konosuba 2]",
		"url":	"https://www.youtube.com/watch?v=a5E4_uFYFJ0",
		"status":	"present"
	}, {
		"artist":	"",
		"title":	"Motteke! Sailor Fuku! [Lucky Star]",
		"url":	"https://www.youtube.com/watch?v=ieQ1rAIjzXc",
		"status":	"present"
	}, {
		"artist":	"",
		"title":	"Connect [Puella Magi Madoka Magica]",
		"url":	"https://www.youtube.com/watch?v=OrgpX-_bFqM",
		"status":	"present"
	}, {
		"artist":	"",
		"title":	"Tempest [Demon Lord, Retry!]",
		"url":	"https://www.youtube.com/watch?v=_rMNE0sVQG4",
		"status":	"present"
	}, {
		"artist":	"",
		"title":	"Asterisk [Bleach]",
		"url":	"https://www.youtube.com/watch?v=_ty-Nqm4Pdc",
		"status":	"present"
	}, {
		"artist":	"",
		"title":	"Snow Fairy [Fairy Tail]",
		"url":	"https://www.youtube.com/watch?v=9jvVBVcZ0-Y",
		"status":	"present"
	}, {
		"artist":	"",
		"title":	"Sense of Wonder [Fairy Tail]",
		"url":	"https://www.youtube.com/watch?v=ITpSB6oESTs",
		"status":	"present"
	}, {
		"artist":	"",
		"title":	"Ft [Fairy Tail]",
		"url":	"https://www.youtube.com/watch?v=T60pzAKu60Q",
		"status":	"present"
	}, {
		"artist":	"",
		"title":	"Rockin' Playing Game [Fairy Tail]",
		"url":	"https://www.youtube.com/watch?v=KTx-7Z8EZos",
		"status":	"present"
	}, {
		"artist":	"",
		"title":	"Egao no Mahou [Fairy Tail]",
		"url":	"https://www.youtube.com/watch?v=xtZBNl3nYUA",
		"status":	"present"
	}, {
		"artist":	"",
		"title":	"Fiesta [Fairy Tail]",
		"url":	"https://www.youtube.com/watch?v=FwHU32HL3SE",
		"status":	"present"
	}, {
		"artist":	"",
		"title":	"Evidence [Fairy Tail]",
		"url":	"https://www.youtube.com/watch?v=TnSxc64_pr4",
		"status":	"present"
	}, {
		"artist":	"",
		"title":	"Rock City Boy [Fairy Tail]",
		"url":	"https://www.youtube.com/watch?v=aVMUbTT-acI",
		"status":	"present"
	}, {
		"artist":	"",
		"title":	"Towa no Kizuna [Fairy Tail]",
		"url":	"https://www.youtube.com/watch?v=0WVkE5CXej0",
		"status":	"present"
	}, {
		"artist":	"",
		"title":	"I Wish [Fairy Tail]",
		"url":	"https://www.youtube.com/watch?v=ckoolMJBICQ",
		"status":	"present"
	}, {
		"artist":	"",
		"title":	"Hajimari no Sora [Fairy Tail]",
		"url":	"https://www.youtube.com/watch?v=nSuYPS4HiWQ",
		"status":	"present"
	}, {
		"artist":	"",
		"title":	"Tenohira [Fairy Tail]",
		"url":	"https://www.youtube.com/watch?v=R5sa0Yl8RVU",
		"status":	"present"
	}, {
		"artist":	"",
		"title":	"Breakthrough [Fairy Tail]",
		"url":	"https://www.youtube.com/watch?v=Ou2yNSDjYbg",
		"status":	"present"
	}, {
		"artist":	"",
		"title":	"Yakusoku no Hi e [Fairy Tail]",
		"url":	"https://www.youtube.com/watch?v=1wdp7Ndnpxw",
		"status":	"present"
	}, {
		"artist":	"",
		"title":	"Masayume Chasing [Fairy Tail (2014)]",
		"url":	"https://www.youtube.com/watch?v=ZQdWnuzJqkw",
		"status":	"present"
	}, {
		"artist":	"",
		"title":	"Strike Back [Fairy Tail (2014)]",
		"url":	"https://www.youtube.com/watch?v=m6cJaI1Z_v4",
		"status":	"error"
	}, {
		"artist":	"",
		"title":	"Mysterius Magic [Fairy Tail (2014)]",
		"url":	"https://www.youtube.com/watch?v=qpvkFgW109I",
		"status":	"present"
	}, {
		"artist":	"",
		"title":	"Break Out [Fairy Tail (2014)]",
		"url":	"https://www.youtube.com/watch?v=6vfucB0hcbA",
		"status":	"error"
	}, {
		"artist":	"",
		"title":	"Yume-iro Graffiti [Fairy Tail (2014)]",
		"url":	"https://www.youtube.com/watch?v=Pq_b_LK-L9U",
		"status":	"present"
	}, {
		"artist":	"",
		"title":	"Neverend Tale [Fairy Tail (2014)]",
		"url":	"https://www.youtube.com/watch?v=3nKD5sPumiA",
		"status":	"present"
	}, {
		"artist":	"",
		"title":	"Belive in Myself [Fairy Tail (2014)]",
		"url":	"https://www.youtube.com/watch?v=MkBVsAYUc-g",
		"status":	"present"
	}, {
		"artist":	"",
		"title":	"Ashita wo Narase [Fairy Tail (2014)]",
		"url":	"https://www.youtube.com/watch?v=e-7uuV7B7mo",
		"status":	"present"
	}, {
		"artist":	"",
		"title":	"Power of the Dream [Fairy Tail: Final Series]",
		"url":	"https://www.youtube.com/watch?v=hjQVOEWehBU",
		"status":	"present"
	}, {
		"artist":	"",
		"title":	"Down by Law [Fairy Tail: Final Series]",
		"url":	"https://www.youtube.com/watch?v=TwiBYcsWwS0",
		"status":	"present"
	}, {
		"artist":	"",
		"title":	"No Limit [Fairy Tail: Final Series]",
		"url":	"https://www.youtube.com/watch?v=yuL_spE1IF8",
		"status":	"present"
	}, {
		"artist":	"",
		"title":	"More than Like [Fairy Tail: Final Series]",
		"url":	"https://www.youtube.com/watch?v=ze6M2tYME9s",
		"status":	"present"
	}, {
		"artist":	"",
		"title":	"Literature [The Journey of Elaina]",
		"url":	"https://www.youtube.com/watch?v=7u9MtqfcWaU",
		"status":	"present"
	}, {
		"artist":	"",
		"title":	"chocolate insomnia [Monogatari Series: Second Season]",
		"url":	"https://www.youtube.com/watch?v=_tSJhgUpfLk",
		"status":	"present"
	}, {
		"artist":	"",
		"title":	"Happy bite [Monogatari Series: Second Season]",
		"url":	"https://www.youtube.com/watch?v=R03ez4e5shQ",
		"status":	"present"
	}, {
		"artist":	"",
		"title":	"Mousou Express [Monogatari Series: Second Season]",
		"url":	"https://www.youtube.com/watch?v=7OGQ0KRitvI",
		"status":	"present"
	}, {
		"artist":	"",
		"title":	"White Lies [Monogatari Series: Second Season]",
		"url":	"https://www.youtube.com/watch?v=j-ks1F9bpik",
		"status":	"present"
	}, {
		"artist":	"",
		"title":	"Fast Love [Monogatari Series: Second Season]",
		"url":	"https://www.youtube.com/watch?v=lpt25kl0Lso",
		"status":	"present"
	}, {
		"artist":	"",
		"title":	"Naked Dive [Myriad Colors Phantom World]",
		"url":	"https://www.youtube.com/watch?v=eszN0xTFBv8",
		"status":	"present"
	}, {
		"artist":	"",
		"title":	"Tabibito no Uta [Mushoku Tensei]",
		"url":	"https://www.youtube.com/watch?v=QG8UZUahRbI",
		"status":	"present"
	}, {
		"artist":	"",
		"title":	"Mezame no Uta [Mushoku Tensei]",
		"url":	"https://www.youtube.com/watch?v=5ZzSxI2HGSs",
		"status":	"error"
	}, {
		"artist":	"",
		"title":	"Keishou no Uta [Mushoku Tensei part 2]",
		"url":	"https://www.youtube.com/watch?v=Fr46aDV1am4",
		"status":	"error"
	}, {
		"artist":	"",
		"title":	"Inori no Uta [Mushoku Tensei part 2]",
		"url":	"https://www.youtube.com/watch?v=A6jB63n5QCM",
		"status":	"error"
	}, {
		"artist":	"",
		"title":	"Toku no komori no uta [Mushoku Tensei part 2]",
		"url":	"https://www.youtube.com/watch?v=gJG6HX7vJcs",
		"status":	"error"
	}, {
		"artist":	"",
		"title":	"Kuusou Mesorogiwi [The Future Diary]",
		"url":	"https://www.youtube.com/watch?v=FPQ9qXb8_vk",
		"status":	"error"
	}, {
		"artist":	"",
		"title":	"Dead End [The Future Diary]",
		"url":	"https://www.youtube.com/watch?v=0_36iNzrEn0",
		"status":	"present"
	}, {
		"artist":	"",
		"title":	"Netsujou no Spectrum [The Seven Deadly Sins]",
		"url":	"https://www.youtube.com/watch?v=Oc9NgPgUO3E",
		"status":	"present"
	}, {
		"artist":	"",
		"title":	"Seven Deadly Sins [The Seven Deadly Sins]",
		"url":	"https://www.youtube.com/watch?v=mRKZ7P79llw",
		"status":	"present"
	}, {
		"artist":	"",
		"title":	"Hikari Are [The Seven Deadly Sins: Dragon's Judgement]",
		"url":	"https://www.youtube.com/watch?v=cvAza2ULRXo",
		"status":	"present"
	}, {
		"artist":	"",
		"title":	"Eien no Aria [The Seven Deadly Sins: Dragon's Judgement]",
		"url":	"https://www.youtube.com/watch?v=IqzXkPiFVAw",
		"status":	"present"
	}, {
		"artist":	"",
		"title":	"Howling [The Seven Deadly Sins: Revival of the Commandments]",
		"url":	"https://www.youtube.com/watch?v=oI1-CxBkJeY",
		"status":	"error"
	}, {
		"artist":	"",
		"title":	"Ame ga Furu kara Niji ga Deru [The Seven Deadly Sins: Revival of the Commandments]",
		"url":	"https://www.youtube.com/watch?v=G5EY_tfaQmw",
		"status":	"present"
	}, {
		"artist":	"",
		"title":	"Rob the Frontier [The Seven Deadly Sins: Wrath of the Gods]",
		"url":	"https://www.youtube.com/watch?v=fo4MzYmBzHs",
		"status":	"present"
	}, {
		"artist":	"",
		"title":	"Delete [The Seven Deadly Sins: Wrath of the Gods]",
		"url":	"https://www.youtube.com/watch?v=OVtX2SKkvj8",
		"status":	"present"
	}, {
		"artist":	"",
		"title":	"Perfect Slumbers [Nekomonogatari Black]",
		"url":	"https://www.youtube.com/watch?v=MdMH9K4L-4g",
		"status":	"present"
	}, {
		"artist":	"",
		"title":	"Click [Nisekoi]",
		"url":	"https://www.youtube.com/watch?v=nDq9-vNcmAc",
		"status":	"error"
	}, {
		"artist":	"",
		"title":	"Step [Nisekoi]",
		"url":	"https://www.youtube.com/watch?v=K_XuoTpacRY",
		"status":	"error"
	}, {
		"artist":	"",
		"title":	"Rally Go Round [Nisekoi:]",
		"url":	"https://www.youtube.com/watch?v=tI0EjXQo_Oc",
		"status":	"error"
	}, {
		"artist":	"",
		"title":	"Futakotome [Nisemonogatari]",
		"url":	"https://www.youtube.com/watch?v=1LKYgC4QB6I",
		"status":	"present"
	}, {
		"artist":	"",
		"title":	"Marshmallow Justice [Nisemonogatari]",
		"url":	"https://www.youtube.com/watch?v=mdXJHw2N_7Q",
		"status":	"present"
	}, {
		"artist":	"",
		"title":	"Platinum Disco [Nisemonogatari]",
		"url":	"https://www.youtube.com/watch?v=71bXPAIVwAE",
		"status":	"present"
	}, {
		"artist":	"",
		"title":	"Thei Game [No Game No Life]",
		"url":	"https://www.youtube.com/watch?v=6CBp4qylX6I",
		"status":	"present"
	}, {
		"artist":	"",
		"title":	"Goya no Machiawase [Noragami]",
		"url":	"https://www.youtube.com/watch?v=gWCnKoEgfP0",
		"status":	"present"
	}, {
		"artist":	"",
		"title":	"Tabi no Tochuu [Spice and Wolf]",
		"url":	"https://www.youtube.com/watch?v=MN_WgwEmRaw",
		"status":	"present"
	}, {
		"artist":	"",
		"title":	"Clattanoia [Overlord]",
		"url":	"https://www.youtube.com/watch?v=k5H5cxmZL-A",
		"status":	"error"
	}, {
		"artist":	"",
		"title":	"Go Cry Go [Overlord II]",
		"url":	"https://www.youtube.com/watch?v=v4OKxyQdTvg",
		"status":	"present"
	}, {
		"artist":	"",
		"title":	"Voracity [Overlord III]",
		"url":	"https://www.youtube.com/watch?v=611k184Ia3E",
		"status":	"present"
	}, {
		"artist":	"",
		"title":	"Decent Black [Owarimonogatari]",
		"url":	"https://www.youtube.com/watch?v=A0Iw47S3z90",
		"status":	"present"
	}, {
		"artist":	"",
		"title":	"Mathemagics [Owarimonogatari]",
		"url":	"https://www.youtube.com/watch?v=F_Cr9vZ08Ws",
		"status":	"present"
	}, {
		"artist":	"",
		"title":	"Yuudachi Houteishiki [Owarimonogatari]",
		"url":	"https://www.youtube.com/watch?v=aoV0PKHdWXw",
		"status":	"present"
	}, {
		"artist":	"",
		"title":	"Mein Schatz [Owarimonogatari]",
		"url":	"https://www.youtube.com/watch?v=FJ58Dk_cJKA",
		"status":	"present"
	}, {
		"artist":	"",
		"title":	"Terminal Terminal [Owarimonogatari 2nd Season]",
		"url":	"https://www.youtube.com/watch?v=6slgHkcpRoU",
		"status":	"present"
	}, {
		"artist":	"",
		"title":	"Dreamy Date Drive [Owarimonogatari 2nd Season]",
		"url":	"https://www.youtube.com/watch?v=IUv14HK_EUk",
		"status":	"present"
	}, {
		"artist":	"",
		"title":	"Dark Cherry Mystery [Owarimonogatari 2nd Season]",
		"url":	"https://www.youtube.com/watch?v=hhxmwHErUhU",
		"status":	"present"
	}, {
		"artist":	"",
		"title":	"Plunderer [Plunderer]",
		"url":	"https://www.youtube.com/watch?v=1jVHUO5qVJM",
		"status":	"present"
	}, {
		"artist":	"",
		"title":	"Kokou no Hikari Lonely Dark [Plunderer]",
		"url":	"https://www.youtube.com/watch?v=NRCcrLuG4MM",
		"status":	"present"
	}, {
		"artist":	"",
		"title":	"Redo [Re:Zero]",
		"url":	"https://www.youtube.com/watch?v=EV4Tc014Hek",
		"status":	"present"
	}, {
		"artist":	"",
		"title":	"Paradisius Paradoksum [Re:Zero]",
		"url":	"https://www.youtube.com/watch?v=6Af7lOubjf4",
		"status":	"present"
	}, {
		"artist":	"",
		"title":	"Realize [Re:Zero 2nd season]",
		"url":	"https://www.youtube.com/watch?v=AwHapidVQlI",
		"status":	"present"
	}, {
		"artist":	"",
		"title":	"Long Shot [Re:Zero 2nd season 2 Part 2]",
		"url":	"https://www.youtube.com/watch?v=lUmLhQBGtYw",
		"status":	"present"
	}, {
		"artist":	"",
		"title":	"Kyoumei no True Force [Blade Dance of the Elementalers]",
		"url":	"https://www.youtube.com/watch?v=E69e32sSLfU",
		"status":	"present"
	}, {
		"artist":	"",
		"title":	"Kimi no Sei [Rascal Does Not Dream of Bunny Girl Senpai]",
		"url":	"https://www.youtube.com/watch?v=hL011v_heIs",
		"status":	"error"
	}, {
		"artist":	"",
		"title":	"Hikaru Nara [Your Lie in April]",
		"url":	"https://www.youtube.com/watch?v=5_iuNaULT5k",
		"status":	"error"
	}, {
		"artist":	"",
		"title":	"Nanairo Symphony [Your Lie in April]",
		"url":	"https://www.youtube.com/watch?v=fWRaQ_S48R0",
		"status":	"error"
	}, {
		"artist":	"",
		"title":	"Tit for Tat [Cautious Hero]",
		"url":	"https://www.youtube.com/watch?v=rqJg9Syyjq0",
		"status":	"present"
	}, {
		"artist":	"",
		"title":	"Guren no Yumiya [Attack on Titan]",
		"url":	"https://www.youtube.com/watch?v=8OkpRK2_gVs",
		"status":	"present"
	}, {
		"artist":	"",
		"title":	"Jiyuu no Tsubasa [Attack on Titan]",
		"url":	"https://www.youtube.com/watch?v=PbWFpzi8C94",
		"status":	"present"
	}, {
		"artist":	"",
		"title":	"Shinzou wo Sasageyo [Attack on Titan Season 2]",
		"url":	"https://www.youtube.com/watch?v=WAoPeG1LU1g",
		"status":	"present"
	}, {
		"artist":	"",
		"title":	"Red Swan [Attack on Titan Season 3]",
		"url":	"https://www.youtube.com/watch?v=swwUoExDIng",
		"status":	"present"
	}, {
		"artist":	"",
		"title":	"Shoukei to Shikabane no Michi [Attack on Titan Season 3 Part 2]",
		"url":	"https://www.youtube.com/watch?v=jhYg5NrN-r8",
		"status":	"present"
	}, {
		"artist":	"",
		"title":	"My War [Attack on Titan: The Final Season]",
		"url":	"https://www.youtube.com/watch?v=w2y715XAmso",
		"status":	"present"
	}, {
		"artist":	"",
		"title":	"The Rumbling [Attack on Titan: The Final Season Part 2]",
		"url":	"https://www.youtube.com/watch?v=2S4qGKmzBJE",
		"status":	"present"
	}, {
		"artist":	"",
		"title":	"Gudafuwa Every Day [I've Been Killing Slimes for 300 Years and Maxed Out My Level]",
		"url":	"https://www.youtube.com/watch?v=n6q-99Q0BlI",
		"status":	"present"
	}, {
		"artist":	"",
		"title":	"Hacking to the Gate [Steins;Gate]",
		"url":	"https://www.youtube.com/watch?v=ZGM90Bo3zH0",
		"status":	"present"
	}, {
		"artist":	"",
		"title":	"Crossing Field [Sword Art Online]",
		"url":	"https://www.youtube.com/watch?v=vI8W_XYT29Q",
		"status":	"error"
	}, {
		"artist":	"",
		"title":	"Innocence [Sword Art Online]",
		"url":	"https://www.youtube.com/watch?v=O8T2u83GIiI",
		"status":	"error"
	}, {
		"artist":	"",
		"title":	"Ignite [Sword Art Online II]",
		"url":	"https://www.youtube.com/watch?v=frw21EeOrV0",
		"status":	"error"
	}, {
		"artist":	"",
		"title":	"Courage [Sword Art Online II]",
		"url":	"https://www.youtube.com/watch?v=3n569HxD2Rk",
		"status":	"error"
	}, {
		"artist":	"",
		"title":	"Adamas [Sword Art Online: Alicization]",
		"url":	"https://www.youtube.com/watch?v=i_Y-GwM6o5M",
		"status":	"present"
	}, {
		"artist":	"",
		"title":	"Resister [Sword Art Online: Alicization]",
		"url":	"https://www.youtube.com/watch?v=uEO_D0Cz2R8",
		"status":	"error"
	}, {
		"artist":	"",
		"title":	"Rise [The Rising of the Shield Hero]",
		"url":	"https://www.youtube.com/watch?v=lzsow8bnT3Y",
		"status":	"present"
	}, {
		"artist":	"",
		"title":	"Faith [The Rising of the Shield Hero]",
		"url":	"https://www.youtube.com/watch?v=9wtlzZG0_Bg",
		"status":	"error"
	}, {
		"artist":	"",
		"title":	"Nameless Story [That Time I Got Reincarnated as a Slime]",
		"url":	"https://www.youtube.com/watch?v=GhGTc6p8sg0",
		"status":	"present"
	}, {
		"artist":	"",
		"title":	"Meguru Mono [That Time I Got Reincarnated as a Slime]",
		"url":	"https://www.youtube.com/watch?v=N6yx38obFek",
		"status":	"present"
	}, {
		"artist":	"",
		"title":	"Storyteller [That Time I Got Reincarnated as a Slime Season 2]",
		"url":	"https://www.youtube.com/watch?v=XQqQqK9ufo8",
		"status":	"present"
	}, {
		"artist":	"",
		"title":	"Like Flames [That Time I Got Reincarnated as a Slime Season 2 Part 2]",
		"url":	"https://www.youtube.com/watch?v=jEDQmD7nhyQ",
		"status":	"present"
	}, {
		"artist":	"",
		"title":	"Brand New Diary [The Slime Diaries]",
		"url":	"https://www.youtube.com/watch?v=huuLekCNAGk",
		"status":	"present"
	}, {
		"artist":	"",
		"title":	"Shadow is the Light [A Certain Scientific Accelerator]",
		"url":	"https://www.youtube.com/watch?v=TQTam1zQe0o",
		"status":	"present"
	}, {
		"artist":	"",
		"title":	"Only My Railgun [A Certain Scientific Railgun]",
		"url":	"https://www.youtube.com/watch?v=q_sQUK418mM",
		"status":	"present"
	}, {
		"artist":	"",
		"title":	"Level 5 [A Certain Scientific Railgun]",
		"url":	"https://www.youtube.com/watch?v=1NYUKIZCV5k",
		"status":	"present"
	}, {
		"artist":	"",
		"title":	"Sister's noise [A Certain Scientific Railgun S]",
		"url":	"https://www.youtube.com/watch?v=R3shsgKbd_M",
		"status":	"error"
	}, {
		"artist":	"",
		"title":	"Eternal Reality [A Certain Scientific Railgun S]",
		"url":	"https://www.youtube.com/watch?v=VNotN0dDMLc",
		"status":	"error"
	}, {
		"artist":	"",
		"title":	"Psi-missing [A Certain Magical Index]",
		"url":	"https://www.youtube.com/watch?v=fv2Ybecq92E",
		"status":	"present"
	}, {
		"artist":	"",
		"title":	"Masterpiece [A Certain Magical Index]",
		"url":	"https://www.youtube.com/watch?v=Q34iirTNwr4",
		"status":	"present"
	}, {
		"artist":	"",
		"title":	"No Buts [A Certain Magical Index II]",
		"url":	"https://www.youtube.com/watch?v=YKvnc7z0roM",
		"status":	"present"
	}, {
		"artist":	"",
		"title":	"See visions [A Certain Magical Index II]",
		"url":	"https://www.youtube.com/watch?v=uqEwvVIeFr4",
		"status":	"present"
	}, {
		"artist":	"",
		"title":	"Jingo Jungle [Saga of Tanya the Evil]",
		"url":	"https://www.youtube.com/watch?v=cOD9g8lY8zA",
		"status":	"present"
	}, {
		"artist":	"",
		"title":	"Hitorigoto [Eromanga Sensei]",
		"url":	"https://www.youtube.com/watch?v=DeGw8-KwxM4",
		"status":	"present"
	}, {
		"artist":	"",
		"title":	"Monochrome no Kiss [Black Butler]",
		"url":	"https://www.youtube.com/watch?v=Nfs1BWgHcnA",
		"status":	"error"
	}]